{
    "metadata": {
        "lastFrame": 9567,
        "playedOn": "dolphin",
        "players": {
            "0": {
                "characters": {
                    "24": 15209
                },
                "names": {
                    "code": "ABEF#110",
                    "netplay": "Abefroman"
                }
            },
            "1": {
                "characters": {
                    "25": 15209
                },
                "names": {
                    "code": "GRVN#0",
                    "netplay": "Groovin'"
                }
            }
        },
        "startAt": "2021-08-30T06:10:52Z"
    },
    "players": [
        {
            "blackStockIcon": false,
            "characterColor": 0,
            "characterId": 3,
            "connectCode": "ABEF#110",
            "controllerFix": "UCF",
            "cpuLevel": 1,
            "defenseRatio": 1,
            "displayName": "Abefroman",
            "handicap": 9,
            "invisible": false,
            "lowGravity": false,
            "metal": false,
            "modelScale": 1,
            "nametag": "",
            "offenseRatio": 1,
            "playerIndex": 0,
            "port": 1,
            "rumbleEnabled": false,
            "silentCharacter": false,
            "staminaMode": false,
            "startOnAngelPlatform": false,
            "startStocks": 4,
            "teamId": 0,
            "teamShade": 0,
            "type": 0,
            "userId": ""
        },
        {
            "blackStockIcon": false,
            "characterColor": 0,
            "characterId": 25,
            "connectCode": "GRVN#0",
            "controllerFix": "UCF",
            "cpuLevel": 1,
            "defenseRatio": 1,
            "displayName": "Groovin'",
            "handicap": 9,
            "invisible": false,
            "lowGravity": false,
            "metal": false,
            "modelScale": 1,
            "nametag": "",
            "offenseRatio": 1,
            "playerIndex": 1,
            "port": 2,
            "rumbleEnabled": false,
            "silentCharacter": false,
            "staminaMode": false,
            "startOnAngelPlatform": false,
            "startStocks": 4,
            "teamId": 1,
            "teamShade": 0,
            "type": 0,
            "userId": ""
        }
    ],
    "stats": {
        "actionCounts": [
            {
                "airDodgeCount": 2,
                "attackCount": {
                    "bair": 5,
                    "dair": 22,
                    "dash": 6,
                    "dsmash": 1,
                    "dtilt": 5,
                    "fair": 27,
                    "fsmash": 1,
                    "ftilt": 2,
                    "jab1": 0,
                    "jab2": 0,
                    "jab3": 0,
                    "jabm": 0,
                    "nair": 5,
                    "uair": 4,
                    "usmash": 1,
                    "utilt": 5
                },
                "dashDanceCount": 13,
                "grabCount": {
                    "fail": 2,
                    "success": 2
                },
                "groundTechCount": {
                    "away": 0,
                    "fail": 5,
                    "in": 0,
                    "neutral": 1
                },
                "lCancelCount": {
                    "fail": 7,
                    "success": 33
                },
                "ledgegrabCount": 6,
                "playerIndex": 0,
                "rollCount": 0,
                "spotDodgeCount": 0,
                "throwCount": {
                    "back": 0,
                    "down": 1,
                    "forward": 1,
                    "up": 0
                },
                "wallTechCount": {
                    "fail": 0,
                    "success": 0
                },
                "wavedashCount": 12,
                "wavelandCount": 6
            },
            {
                "airDodgeCount": 1,
                "attackCount": {
                    "bair": 12,
                    "dair": 10,
                    "dash": 0,
                    "dsmash": 1,
                    "dtilt": 5,
                    "fair": 22,
                    "fsmash": 2,
                    "ftilt": 0,
                    "jab1": 9,
                    "jab2": 0,
                    "jab3": 0,
                    "jabm": 0,
                    "nair": 2,
                    "uair": 6,
                    "usmash": 2,
                    "utilt": 0
                },
                "dashDanceCount": 7,
                "grabCount": {
                    "fail": 2,
                    "success": 2
                },
                "groundTechCount": {
                    "away": 1,
                    "fail": 4,
                    "in": 3,
                    "neutral": 1
                },
                "lCancelCount": {
                    "fail": 2,
                    "success": 29
                },
                "ledgegrabCount": 4,
                "playerIndex": 1,
                "rollCount": 1,
                "spotDodgeCount": 1,
                "throwCount": {
                    "back": 0,
                    "down": 2,
                    "forward": 0,
                    "up": 0
                },
                "wallTechCount": {
                    "fail": 0,
                    "success": 0
                },
                "wavedashCount": 0,
                "wavelandCount": 5
            }
        ],
        "combos": [
            {
                "currentPercent": 9,
                "didKill": false,
                "endFrame": 105,
                "endPercent": 9,
                "lastHitBy": 0,
                "moves": [
                    {
                        "damage": 9,
                        "frame": 38,
                        "hitCount": 1,
                        "moveId": 8,
                        "playerIndex": 0
                    }
                ],
                "playerIndex": 1,
                "startFrame": 38,
                "startPercent": 0
            },
            {
                "currentPercent": 16,
                "didKill": false,
                "endFrame": 219,
                "endPercent": 16,
                "lastHitBy": 0,
                "moves": [
                    {
                        "damage": 7,
                        "frame": 153,
                        "hitCount": 1,
                        "moveId": 16,
                        "playerIndex": 0
                    }
                ],
                "playerIndex": 1,
                "startFrame": 153,
                "startPercent": 9
            },
            {
                "currentPercent": 17,
                "didKill": false,
                "endFrame": 337,
                "endPercent": 17,
                "lastHitBy": 1,
                "moves": [
                    {
                        "damage": 17,
                        "frame": 247,
                        "hitCount": 1,
                        "moveId": 14,
                        "playerIndex": 1
                    }
                ],
                "playerIndex": 0,
                "startFrame": 247,
                "startPercent": 0
            },
            {
                "currentPercent": 29,
                "didKill": false,
                "endFrame": 414,
                "endPercent": 29,
                "lastHitBy": 0,
                "moves": [
                    {
                        "damage": 13,
                        "frame": 340,
                        "hitCount": 1,
                        "moveId": 17,
                        "playerIndex": 0
                    }
                ],
                "playerIndex": 1,
                "startFrame": 340,
                "startPercent": 16
            },
            {
                "currentPercent": 40.83000183105469,
                "didKill": false,
                "endFrame": 514,
                "endPercent": 40.83000183105469,
                "lastHitBy": 0,
                "moves": [
                    {
                        "damage": 11.830001831054688,
                        "frame": 440,
                        "hitCount": 1,
                        "moveId": 17,
                        "playerIndex": 0
                    }
                ],
                "playerIndex": 1,
                "startFrame": 440,
                "startPercent": 29
            },
            {
                "currentPercent": 65.29000091552734,
                "didKill": false,
                "endFrame": 764,
                "endPercent": 65.29000091552734,
                "lastHitBy": 0,
                "moves": [
                    {
                        "damage": 8.459999084472656,
                        "frame": 625,
                        "hitCount": 1,
                        "moveId": 8,
                        "playerIndex": 0
                    },
                    {
                        "damage": 16,
                        "frame": 665,
                        "hitCount": 1,
                        "moveId": 14,
                        "playerIndex": 0
                    }
                ],
                "playerIndex": 1,
                "startFrame": 625,
                "startPercent": 40.83000183105469
            },
            {
                "currentPercent": 96.73999786376953,
                "didKill": false,
                "endFrame": 1010,
                "endPercent": 96.73999786376953,
                "lastHitBy": 0,
                "moves": [
                    {
                        "damage": 15.569999694824219,
                        "frame": 807,
                        "hitCount": 2,
                        "moveId": 18,
                        "playerIndex": 0
                    },
                    {
                        "damage": 14.879997253417969,
                        "frame": 878,
                        "hitCount": 1,
                        "moveId": 14,
                        "playerIndex": 0
                    },
                    {
                        "damage": 1,
                        "frame": 960,
                        "hitCount": 1,
                        "moveId": 14,
                        "playerIndex": 0
                    }
                ],
                "playerIndex": 1,
                "startFrame": 807,
                "startPercent": 65.29000091552734
            },
            {
                "currentPercent": 33,
                "didKill": false,
                "endFrame": 1470,
                "endPercent": 33,
                "lastHitBy": 1,
                "moves": [
                    {
                        "damage": 16,
                        "frame": 1388,
                        "hitCount": 1,
                        "moveId": 15,
                        "playerIndex": 1
                    }
                ],
                "playerIndex": 0,
                "startFrame": 1388,
                "startPercent": 17
            },
            {
                "currentPercent": 6,
                "didKill": false,
                "endFrame": 1532,
                "endPercent": 6,
                "lastHitBy": 0,
                "moves": [
                    {
                        "damage": 6,
                        "frame": 1462,
                        "hitCount": 1,
                        "moveId": 10,
                        "playerIndex": 0
                    }
                ],
                "playerIndex": 1,
                "startFrame": 1462,
                "startPercent": 0
            },
            {
                "currentPercent": 73.87999725341797,
                "didKill": false,
                "endFrame": 1862,
                "endPercent": 73.87999725341797,
                "lastHitBy": 1,
                "moves": [
                    {
                        "damage": 7,
                        "frame": 1499,
                        "hitCount": 1,
                        "moveId": 2,
                        "playerIndex": 1
                    },
                    {
                        "damage": 17,
                        "frame": 1547,
                        "hitCount": 1,
                        "moveId": 14,
                        "playerIndex": 1
                    },
                    {
                        "damage": 1,
                        "frame": 1656,
                        "hitCount": 1,
                        "moveId": 14,
                        "playerIndex": 1
                    },
                    {
                        "damage": 14.879997253417969,
                        "frame": 1741,
                        "hitCount": 1,
                        "moveId": 15,
                        "playerIndex": 1
                    }
                ],
                "playerIndex": 0,
                "startFrame": 1499,
                "startPercent": 33
            },
            {
                "currentPercent": 95.87999725341797,
                "didKill": true,
                "endFrame": 2210,
                "endPercent": 95.87999725341797,
                "lastHitBy": 1,
                "moves": [
                    {
                        "damage": 22,
                        "frame": 2006,
                        "hitCount": 1,
                        "moveId": 17,
                        "playerIndex": 1
                    }
                ],
                "playerIndex": 0,
                "startFrame": 2006,
                "startPercent": 73.87999725341797
            },
            {
                "currentPercent": 12,
                "didKill": false,
                "endFrame": 2564,
                "endPercent": 12,
                "lastHitBy": 0,
                "moves": [
                    {
                        "damage": 6,
                        "frame": 2495,
                        "hitCount": 1,
                        "moveId": 14,
                        "playerIndex": 0
                    }
                ],
                "playerIndex": 1,
                "startFrame": 2495,
                "startPercent": 6
            },
            {
                "currentPercent": 6.579999923706055,
                "didKill": false,
                "endFrame": 2599,
                "endPercent": 6.579999923706055,
                "lastHitBy": 1,
                "moves": [
                    {
                        "damage": 6.579999923706055,
                        "frame": 2527,
                        "hitCount": 1,
                        "moveId": 2,
                        "playerIndex": 1
                    }
                ],
                "playerIndex": 0,
                "startFrame": 2527,
                "startPercent": 0
            },
            {
                "currentPercent": 12.59999942779541,
                "didKill": false,
                "endFrame": 2741,
                "endPercent": 12.59999942779541,
                "lastHitBy": 1,
                "moves": [
                    {
                        "damage": 6.0199995040893555,
                        "frame": 2668,
                        "hitCount": 1,
                        "moveId": 2,
                        "playerIndex": 1
                    }
                ],
                "playerIndex": 0,
                "startFrame": 2668,
                "startPercent": 6.579999923706055
            },
            {
                "currentPercent": 31.599998474121094,
                "didKill": false,
                "endFrame": 2987,
                "endPercent": 31.599998474121094,
                "lastHitBy": 1,
                "moves": [
                    {
                        "damage": 6.999999046325684,
                        "frame": 2835,
                        "hitCount": 1,
                        "moveId": 56,
                        "playerIndex": 1
                    },
                    {
                        "damage": 12,
                        "frame": 2886,
                        "hitCount": 1,
                        "moveId": 13,
                        "playerIndex": 1
                    }
                ],
                "playerIndex": 0,
                "startFrame": 2820,
                "startPercent": 12.59999942779541
            },
            {
                "currentPercent": 59.459999084472656,
                "didKill": false,
                "endFrame": 3184,
                "endPercent": 59.459999084472656,
                "lastHitBy": 0,
                "moves": [
                    {
                        "damage": 14,
                        "frame": 2983,
                        "hitCount": 1,
                        "moveId": 17,
                        "playerIndex": 0
                    },
                    {
                        "damage": 5.459999084472656,
                        "frame": 2999,
                        "hitCount": 1,
                        "moveId": 17,
                        "playerIndex": 0
                    },
                    {
                        "damage": 12,
                        "frame": 3036,
                        "hitCount": 1,
                        "moveId": 9,
                        "playerIndex": 0
                    },
                    {
                        "damage": 16,
                        "frame": 3089,
                        "hitCount": 1,
                        "moveId": 13,
                        "playerIndex": 0
                    }
                ],
                "playerIndex": 1,
                "startFrame": 2983,
                "startPercent": 12
            },
            {
                "currentPercent": 71.55000305175781,
                "didKill": false,
                "endFrame": 3417,
                "endPercent": 71.55000305175781,
                "lastHitBy": 0,
                "moves": [
                    {
                        "damage": 12.090003967285156,
                        "frame": 3290,
                        "hitCount": 1,
                        "moveId": 17,
                        "playerIndex": 0
                    }
                ],
                "playerIndex": 1,
                "startFrame": 3290,
                "startPercent": 59.459999084472656
            },
            {
                "currentPercent": 60.97999572753906,
                "didKill": false,
                "endFrame": 3674,
                "endPercent": 60.97999572753906,
                "lastHitBy": 1,
                "moves": [
                    {
                        "damage": 3.729999542236328,
                        "frame": 3432,
                        "hitCount": 4,
                        "moveId": 20,
                        "playerIndex": 1
                    },
                    {
                        "damage": 13.64999771118164,
                        "frame": 3458,
                        "hitCount": 1,
                        "moveId": 20,
                        "playerIndex": 1
                    },
                    {
                        "damage": 12,
                        "frame": 3561,
                        "hitCount": 1,
                        "moveId": 16,
                        "playerIndex": 1
                    }
                ],
                "playerIndex": 0,
                "startFrame": 3430,
                "startPercent": 31.599998474121094
            },
            {
                "currentPercent": 109.41000366210938,
                "didKill": false,
                "endFrame": 3941,
                "endPercent": 109.41000366210938,
                "lastHitBy": 0,
                "moves": [
                    {
                        "damage": 11.900001525878906,
                        "frame": 3683,
                        "hitCount": 1,
                        "moveId": 17,
                        "playerIndex": 0
                    },
                    {
                        "damage": 10.919998168945312,
                        "frame": 3759,
                        "hitCount": 1,
                        "moveId": 17,
                        "playerIndex": 0
                    },
                    {
                        "damage": 15.040000915527344,
                        "frame": 3820,
                        "hitCount": 1,
                        "moveId": 13,
                        "playerIndex": 0
                    }
                ],
                "playerIndex": 1,
                "startFrame": 3683,
                "startPercent": 71.55000305175781
            },
            {
                "currentPercent": 71.89999389648438,
                "didKill": false,
                "endFrame": 4121,
                "endPercent": 71.89999389648438,
                "lastHitBy": 1,
                "moves": [
                    {
                        "damage": 10.919998168945312,
                        "frame": 3995,
                        "hitCount": 1,
                        "moveId": 16,
                        "playerIndex": 1
                    }
                ],
                "playerIndex": 0,
                "startFrame": 3995,
                "startPercent": 60.97999572753906
            },
            {
                "currentPercent": 0,
                "didKill": false,
                "endFrame": 4376,
                "endPercent": 0,
                "lastHitBy": 0,
                "moves": [],
                "playerIndex": 1,
                "startFrame": 4329,
                "startPercent": 0
            },
            {
                "currentPercent": 8,
                "didKill": false,
                "endFrame": 4515,
                "endPercent": 8,
                "lastHitBy": 0,
                "moves": [
                    {
                        "damage": 8,
                        "frame": 4390,
                        "hitCount": 1,
                        "moveId": 56,
                        "playerIndex": 0
                    }
                ],
                "playerIndex": 1,
                "startFrame": 4390,
                "startPercent": 0
            },
            {
                "currentPercent": 23.84000015258789,
                "didKill": false,
                "endFrame": 4572,
                "endPercent": 23.84000015258789,
                "lastHitBy": 0,
                "moves": [
                    {
                        "damage": 15.84000015258789,
                        "frame": 4519,
                        "hitCount": 1,
                        "moveId": 14,
                        "playerIndex": 0
                    }
                ],
                "playerIndex": 1,
                "startFrame": 4519,
                "startPercent": 8
            },
            {
                "currentPercent": 100.89999389648438,
                "didKill": true,
                "endFrame": 4715,
                "endPercent": 100.89999389648438,
                "lastHitBy": 1,
                "moves": [
                    {
                        "damage": 12,
                        "frame": 4553,
                        "hitCount": 1,
                        "moveId": 9,
                        "playerIndex": 1
                    },
                    {
                        "damage": 17,
                        "frame": 4654,
                        "hitCount": 1,
                        "moveId": 14,
                        "playerIndex": 1
                    }
                ],
                "playerIndex": 0,
                "startFrame": 4553,
                "startPercent": 71.89999389648438
            },
            {
                "currentPercent": 43.29999923706055,
                "didKill": false,
                "endFrame": 5033,
                "endPercent": 43.29999923706055,
                "lastHitBy": 0,
                "moves": [
                    {
                        "damage": 14,
                        "frame": 4941,
                        "hitCount": 1,
                        "moveId": 17,
                        "playerIndex": 0
                    },
                    {
                        "damage": 5.459999084472656,
                        "frame": 4967,
                        "hitCount": 1,
                        "moveId": 17,
                        "playerIndex": 0
                    }
                ],
                "playerIndex": 1,
                "startFrame": 4941,
                "startPercent": 23.84000015258789
            },
            {
                "currentPercent": 59.29999923706055,
                "didKill": false,
                "endFrame": 5143,
                "endPercent": 59.29999923706055,
                "lastHitBy": 0,
                "moves": [
                    {
                        "damage": 16,
                        "frame": 5050,
                        "hitCount": 1,
                        "moveId": 14,
                        "playerIndex": 0
                    }
                ],
                "playerIndex": 1,
                "startFrame": 5050,
                "startPercent": 43.29999923706055
            },
            {
                "currentPercent": 12,
                "didKill": false,
                "endFrame": 5214,
                "endPercent": 12,
                "lastHitBy": 1,
                "moves": [
                    {
                        "damage": 12,
                        "frame": 5134,
                        "hitCount": 1,
                        "moveId": 16,
                        "playerIndex": 1
                    }
                ],
                "playerIndex": 0,
                "startFrame": 5134,
                "startPercent": 0
            },
            {
                "currentPercent": 80.38999938964844,
                "didKill": false,
                "endFrame": 5419,
                "endPercent": 80.38999938964844,
                "lastHitBy": 0,
                "moves": [
                    {
                        "damage": 9.000003814697266,
                        "frame": 5239,
                        "hitCount": 1,
                        "moveId": 6,
                        "playerIndex": 0
                    },
                    {
                        "damage": 12.089996337890625,
                        "frame": 5304,
                        "hitCount": 1,
                        "moveId": 17,
                        "playerIndex": 0
                    }
                ],
                "playerIndex": 1,
                "startFrame": 5239,
                "startPercent": 59.29999923706055
            },
            {
                "currentPercent": 106.38999938964844,
                "didKill": false,
                "endFrame": 5737,
                "endPercent": 106.38999938964844,
                "lastHitBy": 0,
                "moves": [
                    {
                        "damage": 10,
                        "frame": 5456,
                        "hitCount": 1,
                        "moveId": 7,
                        "playerIndex": 0
                    },
                    {
                        "damage": 16,
                        "frame": 5530,
                        "hitCount": 1,
                        "moveId": 13,
                        "playerIndex": 0
                    }
                ],
                "playerIndex": 1,
                "startFrame": 5456,
                "startPercent": 80.38999938964844
            },
            {
                "currentPercent": 19,
                "didKill": false,
                "endFrame": 5829,
                "endPercent": 19,
                "lastHitBy": 1,
                "moves": [
                    {
                        "damage": 7,
                        "frame": 5755,
                        "hitCount": 1,
                        "moveId": 2,
                        "playerIndex": 1
                    }
                ],
                "playerIndex": 0,
                "startFrame": 5755,
                "startPercent": 12
            },
            {
                "currentPercent": 41.349998474121094,
                "didKill": false,
                "endFrame": 6276,
                "endPercent": 41.349998474121094,
                "lastHitBy": 1,
                "moves": [
                    {
                        "damage": 6.369998931884766,
                        "frame": 6048,
                        "hitCount": 1,
                        "moveId": 2,
                        "playerIndex": 1
                    },
                    {
                        "damage": 15.979999542236328,
                        "frame": 6100,
                        "hitCount": 1,
                        "moveId": 14,
                        "playerIndex": 1
                    }
                ],
                "playerIndex": 0,
                "startFrame": 6048,
                "startPercent": 19
            },
            {
                "currentPercent": 121.58999633789062,
                "didKill": false,
                "endFrame": 6478,
                "endPercent": 121.58999633789062,
                "lastHitBy": 0,
                "moves": [
                    {
                        "damage": 15.199996948242188,
                        "frame": 6347,
                        "hitCount": 1,
                        "moveId": 14,
                        "playerIndex": 0
                    }
                ],
                "playerIndex": 1,
                "startFrame": 6347,
                "startPercent": 106.38999938964844
            },
            {
                "currentPercent": 148.13999938964844,
                "didKill": true,
                "endFrame": 6777,
                "endPercent": 148.13999938964844,
                "lastHitBy": 0,
                "moves": [
                    {
                        "damage": 8.550003051757812,
                        "frame": 6550,
                        "hitCount": 1,
                        "moveId": 6,
                        "playerIndex": 0
                    },
                    {
                        "damage": 18,
                        "frame": 6630,
                        "hitCount": 1,
                        "moveId": 11,
                        "playerIndex": 0
                    }
                ],
                "playerIndex": 1,
                "startFrame": 6550,
                "startPercent": 121.58999633789062
            },
            {
                "currentPercent": 57.349998474121094,
                "didKill": false,
                "endFrame": 7106,
                "endPercent": 57.349998474121094,
                "lastHitBy": 1,
                "moves": [
                    {
                        "damage": 16,
                        "frame": 6928,
                        "hitCount": 1,
                        "moveId": 15,
                        "playerIndex": 1
                    }
                ],
                "playerIndex": 0,
                "startFrame": 6928,
                "startPercent": 41.349998474121094
            },
            {
                "currentPercent": 12.34999942779541,
                "didKill": false,
                "endFrame": 7252,
                "endPercent": 12.34999942779541,
                "lastHitBy": 0,
                "moves": [
                    {
                        "damage": 12.34999942779541,
                        "frame": 7178,
                        "hitCount": 1,
                        "moveId": 17,
                        "playerIndex": 0
                    }
                ],
                "playerIndex": 1,
                "startFrame": 7178,
                "startPercent": 0
            },
            {
                "currentPercent": 64.3499984741211,
                "didKill": false,
                "endFrame": 7259,
                "endPercent": 64.3499984741211,
                "lastHitBy": 1,
                "moves": [
                    {
                        "damage": 7,
                        "frame": 7210,
                        "hitCount": 1,
                        "moveId": 2,
                        "playerIndex": 1
                    }
                ],
                "playerIndex": 0,
                "startFrame": 7210,
                "startPercent": 57.349998474121094
            },
            {
                "currentPercent": 27.229999542236328,
                "didKill": false,
                "endFrame": 7370,
                "endPercent": 27.229999542236328,
                "lastHitBy": 0,
                "moves": [
                    {
                        "damage": 14.880000114440918,
                        "frame": 7290,
                        "hitCount": 1,
                        "moveId": 14,
                        "playerIndex": 0
                    }
                ],
                "playerIndex": 1,
                "startFrame": 7290,
                "startPercent": 12.34999942779541
            },
            {
                "currentPercent": 32.630001068115234,
                "didKill": false,
                "endFrame": 7493,
                "endPercent": 32.630001068115234,
                "lastHitBy": 0,
                "moves": [
                    {
                        "damage": 5.400001525878906,
                        "frame": 7428,
                        "hitCount": 1,
                        "moveId": 17,
                        "playerIndex": 0
                    }
                ],
                "playerIndex": 1,
                "startFrame": 7428,
                "startPercent": 27.229999542236328
            },
            {
                "currentPercent": 56.900001525878906,
                "didKill": false,
                "endFrame": 7838,
                "endPercent": 56.900001525878906,
                "lastHitBy": 0,
                "moves": [
                    {
                        "damage": 5,
                        "frame": 7551,
                        "hitCount": 1,
                        "moveId": 15,
                        "playerIndex": 0
                    },
                    {
                        "damage": 4.549999237060547,
                        "frame": 7632,
                        "hitCount": 1,
                        "moveId": 15,
                        "playerIndex": 0
                    },
                    {
                        "damage": 14.720001220703125,
                        "frame": 7739,
                        "hitCount": 1,
                        "moveId": 14,
                        "playerIndex": 0
                    }
                ],
                "playerIndex": 1,
                "startFrame": 7551,
                "startPercent": 32.630001068115234
            },
            {
                "currentPercent": 81.73001098632812,
                "didKill": false,
                "endFrame": 8009,
                "endPercent": 81.73001098632812,
                "lastHitBy": 1,
                "moves": [
                    {
                        "damage": 3.730010986328125,
                        "frame": 7864,
                        "hitCount": 4,
                        "moveId": 20,
                        "playerIndex": 1
                    },
                    {
                        "damage": 13.650001525878906,
                        "frame": 7890,
                        "hitCount": 1,
                        "moveId": 20,
                        "playerIndex": 1
                    }
                ],
                "playerIndex": 0,
                "startFrame": 7862,
                "startPercent": 64.3499984741211
            },
            {
                "currentPercent": 88.73001098632812,
                "didKill": false,
                "endFrame": 8214,
                "endPercent": 88.73001098632812,
                "lastHitBy": 1,
                "moves": [
                    {
                        "damage": 7,
                        "frame": 8108,
                        "hitCount": 1,
                        "moveId": 56,
                        "playerIndex": 1
                    }
                ],
                "playerIndex": 0,
                "startFrame": 8084,
                "startPercent": 81.73001098632812
            },
            {
                "currentPercent": 82.8499984741211,
                "didKill": false,
                "endFrame": 8375,
                "endPercent": 82.8499984741211,
                "lastHitBy": 0,
                "moves": [
                    {
                        "damage": 13.599998474121094,
                        "frame": 8180,
                        "hitCount": 1,
                        "moveId": 14,
                        "playerIndex": 0
                    },
                    {
                        "damage": 12.349998474121094,
                        "frame": 8280,
                        "hitCount": 3,
                        "moveId": 15,
                        "playerIndex": 0
                    }
                ],
                "playerIndex": 1,
                "startFrame": 8180,
                "startPercent": 56.900001525878906
            },
            {
                "currentPercent": 95.06999969482422,
                "didKill": false,
                "endFrame": 8493,
                "endPercent": 95.06999969482422,
                "lastHitBy": 0,
                "moves": [
                    {
                        "damage": 12.220001220703125,
                        "frame": 8413,
                        "hitCount": 1,
                        "moveId": 17,
                        "playerIndex": 0
                    }
                ],
                "playerIndex": 1,
                "startFrame": 8413,
                "startPercent": 82.8499984741211
            },
            {
                "currentPercent": 113.80999755859375,
                "didKill": false,
                "endFrame": 8698,
                "endPercent": 113.80999755859375,
                "lastHitBy": 0,
                "moves": [
                    {
                        "damage": 5.099998474121094,
                        "frame": 8535,
                        "hitCount": 1,
                        "moveId": 14,
                        "playerIndex": 0
                    },
                    {
                        "damage": 12.639999389648438,
                        "frame": 8579,
                        "hitCount": 1,
                        "moveId": 14,
                        "playerIndex": 0
                    }
                ],
                "playerIndex": 1,
                "startFrame": 8535,
                "startPercent": 95.06999969482422
            },
            {
                "currentPercent": 139.69000244140625,
                "didKill": false,
                "endFrame": 9065,
                "endPercent": 139.69000244140625,
                "lastHitBy": 0,
                "moves": [
                    {
                        "damage": 12.879997253417969,
                        "frame": 8793,
                        "hitCount": 1,
                        "moveId": 17,
                        "playerIndex": 0
                    },
                    {
                        "damage": 7.000007629394531,
                        "frame": 8914,
                        "hitCount": 1,
                        "moveId": 16,
                        "playerIndex": 0
                    },
                    {
                        "damage": 6,
                        "frame": 8958,
                        "hitCount": 1,
                        "moveId": 20,
                        "playerIndex": 0
                    }
                ],
                "playerIndex": 1,
                "startFrame": 8793,
                "startPercent": 113.80999755859375
            },
            {
                "currentPercent": 139.69000244140625,
                "didKill": false,
                "endFrame": 9215,
                "endPercent": 139.69000244140625,
                "lastHitBy": 0,
                "moves": [],
                "playerIndex": 1,
                "startFrame": 9166,
                "startPercent": 139.69000244140625
            },
            {
                "currentPercent": 148.69000244140625,
                "didKill": false,
                "endFrame": 9343,
                "endPercent": 148.69000244140625,
                "lastHitBy": 0,
                "moves": [
                    {
                        "damage": 8,
                        "frame": 9229,
                        "hitCount": 1,
                        "moveId": 53,
                        "playerIndex": 0
                    }
                ],
                "playerIndex": 1,
                "startFrame": 9229,
                "startPercent": 139.69000244140625
            },
            {
                "currentPercent": 158.69000244140625,
                "didKill": true,
                "endFrame": 9567,
                "endPercent": 158.69000244140625,
                "lastHitBy": 0,
                "moves": [
                    {
                        "damage": 10,
                        "frame": 9394,
                        "hitCount": 1,
                        "moveId": 7,
                        "playerIndex": 0
                    }
                ],
                "playerIndex": 1,
                "startFrame": 9394,
                "startPercent": 148.69000244140625
            }
        ],
        "conversions": [
            {
                "currentPercent": 9,
                "didKill": false,
                "endFrame": 112,
                "endPercent": 9,
                "lastHitBy": 0,
                "moves": [
                    {
                        "damage": 9,
                        "frame": 38,
                        "hitCount": 1,
                        "moveId": 8,
                        "playerIndex": 0
                    }
                ],
                "openingType": "neutral-win",
                "playerIndex": 1,
                "startFrame": 38,
                "startPercent": 0
            },
            {
                "currentPercent": 16,
                "didKill": false,
                "endFrame": 230,
                "endPercent": 16,
                "lastHitBy": 0,
                "moves": [
                    {
                        "damage": 7,
                        "frame": 153,
                        "hitCount": 1,
                        "moveId": 16,
                        "playerIndex": 0
                    }
                ],
                "openingType": "neutral-win",
                "playerIndex": 1,
                "startFrame": 153,
                "startPercent": 9
            },
            {
                "currentPercent": 17,
                "didKill": false,
                "endFrame": 406,
                "endPercent": 17,
                "lastHitBy": 1,
                "moves": [
                    {
                        "damage": 17,
                        "frame": 247,
                        "hitCount": 1,
                        "moveId": 14,
                        "playerIndex": 1
                    }
                ],
                "openingType": "neutral-win",
                "playerIndex": 0,
                "startFrame": 247,
                "startPercent": 0
            },
            {
                "currentPercent": 29,
                "didKill": false,
                "endFrame": 420,
                "endPercent": 29,
                "lastHitBy": 0,
                "moves": [
                    {
                        "damage": 13,
                        "frame": 340,
                        "hitCount": 1,
                        "moveId": 17,
                        "playerIndex": 0
                    }
                ],
                "openingType": "counter-attack",
                "playerIndex": 1,
                "startFrame": 340,
                "startPercent": 16
            },
            {
                "currentPercent": 40.83000183105469,
                "didKill": false,
                "endFrame": 541,
                "endPercent": 40.83000183105469,
                "lastHitBy": 0,
                "moves": [
                    {
                        "damage": 11.830001831054688,
                        "frame": 440,
                        "hitCount": 1,
                        "moveId": 17,
                        "playerIndex": 0
                    }
                ],
                "openingType": "neutral-win",
                "playerIndex": 1,
                "startFrame": 440,
                "startPercent": 29
            },
            {
                "currentPercent": 96.73999786376953,
                "didKill": true,
                "endFrame": 1079,
                "endPercent": 96.73999786376953,
                "lastHitBy": 0,
                "moves": [
                    {
                        "damage": 8.459999084472656,
                        "frame": 625,
                        "hitCount": 1,
                        "moveId": 8,
                        "playerIndex": 0
                    },
                    {
                        "damage": 16,
                        "frame": 665,
                        "hitCount": 1,
                        "moveId": 14,
                        "playerIndex": 0
                    },
                    {
                        "damage": 15.569999694824219,
                        "frame": 807,
                        "hitCount": 2,
                        "moveId": 18,
                        "playerIndex": 0
                    },
                    {
                        "damage": 14.879997253417969,
                        "frame": 878,
                        "hitCount": 1,
                        "moveId": 14,
                        "playerIndex": 0
                    },
                    {
                        "damage": 1,
                        "frame": 960,
                        "hitCount": 1,
                        "moveId": 14,
                        "playerIndex": 0
                    }
                ],
                "openingType": "neutral-win",
                "playerIndex": 1,
                "startFrame": 625,
                "startPercent": 40.83000183105469
            },
            {
                "currentPercent": 33,
                "didKill": false,
                "endFrame": 1474,
                "endPercent": 33,
                "lastHitBy": 1,
                "moves": [
                    {
                        "damage": 16,
                        "frame": 1388,
                        "hitCount": 1,
                        "moveId": 15,
                        "playerIndex": 1
                    }
                ],
                "openingType": "neutral-win",
                "playerIndex": 0,
                "startFrame": 1388,
                "startPercent": 17
            },
            {
                "currentPercent": 6,
                "didKill": false,
                "endFrame": 1564,
                "endPercent": 6,
                "lastHitBy": 0,
                "moves": [
                    {
                        "damage": 6,
                        "frame": 1462,
                        "hitCount": 1,
                        "moveId": 10,
                        "playerIndex": 0
                    }
                ],
                "openingType": "counter-attack",
                "playerIndex": 1,
                "startFrame": 1462,
                "startPercent": 0
            },
            {
                "currentPercent": 95.87999725341797,
                "didKill": true,
                "endFrame": 2210,
                "endPercent": 95.87999725341797,
                "lastHitBy": 1,
                "moves": [
                    {
                        "damage": 7,
                        "frame": 1499,
                        "hitCount": 1,
                        "moveId": 2,
                        "playerIndex": 1
                    },
                    {
                        "damage": 17,
                        "frame": 1547,
                        "hitCount": 1,
                        "moveId": 14,
                        "playerIndex": 1
                    },
                    {
                        "damage": 1,
                        "frame": 1656,
                        "hitCount": 1,
                        "moveId": 14,
                        "playerIndex": 1
                    },
                    {
                        "damage": 14.879997253417969,
                        "frame": 1741,
                        "hitCount": 1,
                        "moveId": 15,
                        "playerIndex": 1
                    },
                    {
                        "damage": 22,
                        "frame": 2006,
                        "hitCount": 1,
                        "moveId": 17,
                        "playerIndex": 1
                    }
                ],
                "openingType": "counter-attack",
                "playerIndex": 0,
                "startFrame": 1499,
                "startPercent": 33
            },
            {
                "currentPercent": 12,
                "didKill": false,
                "endFrame": 2564,
                "endPercent": 12,
                "lastHitBy": 0,
                "moves": [
                    {
                        "damage": 6,
                        "frame": 2495,
                        "hitCount": 1,
                        "moveId": 14,
                        "playerIndex": 0
                    }
                ],
                "openingType": "neutral-win",
                "playerIndex": 1,
                "startFrame": 2495,
                "startPercent": 6
            },
            {
                "currentPercent": 12.59999942779541,
                "didKill": false,
                "endFrame": 2798,
                "endPercent": 12.59999942779541,
                "lastHitBy": 1,
                "moves": [
                    {
                        "damage": 6.579999923706055,
                        "frame": 2527,
                        "hitCount": 1,
                        "moveId": 2,
                        "playerIndex": 1
                    },
                    {
                        "damage": 6.0199995040893555,
                        "frame": 2668,
                        "hitCount": 1,
                        "moveId": 2,
                        "playerIndex": 1
                    }
                ],
                "openingType": "counter-attack",
                "playerIndex": 0,
                "startFrame": 2527,
                "startPercent": 0
            },
            {
                "currentPercent": 31.599998474121094,
                "didKill": false,
                "endFrame": 3010,
                "endPercent": 31.599998474121094,
                "lastHitBy": 1,
                "moves": [
                    {
                        "damage": 6.999999046325684,
                        "frame": 2835,
                        "hitCount": 1,
                        "moveId": 56,
                        "playerIndex": 1
                    },
                    {
                        "damage": 12,
                        "frame": 2886,
                        "hitCount": 1,
                        "moveId": 13,
                        "playerIndex": 1
                    }
                ],
                "openingType": "neutral-win",
                "playerIndex": 0,
                "startFrame": 2820,
                "startPercent": 12.59999942779541
            },
            {
                "currentPercent": 59.459999084472656,
                "didKill": false,
                "endFrame": 3278,
                "endPercent": 59.459999084472656,
                "lastHitBy": 0,
                "moves": [
                    {
                        "damage": 14,
                        "frame": 2983,
                        "hitCount": 1,
                        "moveId": 17,
                        "playerIndex": 0
                    },
                    {
                        "damage": 5.459999084472656,
                        "frame": 2999,
                        "hitCount": 1,
                        "moveId": 17,
                        "playerIndex": 0
                    },
                    {
                        "damage": 12,
                        "frame": 3036,
                        "hitCount": 1,
                        "moveId": 9,
                        "playerIndex": 0
                    },
                    {
                        "damage": 16,
                        "frame": 3089,
                        "hitCount": 1,
                        "moveId": 13,
                        "playerIndex": 0
                    }
                ],
                "openingType": "counter-attack",
                "playerIndex": 1,
                "startFrame": 2983,
                "startPercent": 12
            },
            {
                "currentPercent": 71.55000305175781,
                "didKill": false,
                "endFrame": 3635,
                "endPercent": 71.55000305175781,
                "lastHitBy": 0,
                "moves": [
                    {
                        "damage": 12.090003967285156,
                        "frame": 3290,
                        "hitCount": 1,
                        "moveId": 17,
                        "playerIndex": 0
                    }
                ],
                "openingType": "neutral-win",
                "playerIndex": 1,
                "startFrame": 3290,
                "startPercent": 59.459999084472656
            },
            {
                "currentPercent": 60.97999572753906,
                "didKill": false,
                "endFrame": 3712,
                "endPercent": 60.97999572753906,
                "lastHitBy": 1,
                "moves": [
                    {
                        "damage": 3.729999542236328,
                        "frame": 3432,
                        "hitCount": 4,
                        "moveId": 20,
                        "playerIndex": 1
                    },
                    {
                        "damage": 13.64999771118164,
                        "frame": 3458,
                        "hitCount": 1,
                        "moveId": 20,
                        "playerIndex": 1
                    },
                    {
                        "damage": 12,
                        "frame": 3561,
                        "hitCount": 1,
                        "moveId": 16,
                        "playerIndex": 1
                    }
                ],
                "openingType": "counter-attack",
                "playerIndex": 0,
                "startFrame": 3430,
                "startPercent": 31.599998474121094
            },
            {
                "currentPercent": 109.41000366210938,
                "didKill": true,
                "endFrame": 4073,
                "endPercent": 109.41000366210938,
                "lastHitBy": 0,
                "moves": [
                    {
                        "damage": 11.900001525878906,
                        "frame": 3683,
                        "hitCount": 1,
                        "moveId": 17,
                        "playerIndex": 0
                    },
                    {
                        "damage": 10.919998168945312,
                        "frame": 3759,
                        "hitCount": 1,
                        "moveId": 17,
                        "playerIndex": 0
                    },
                    {
                        "damage": 15.040000915527344,
                        "frame": 3820,
                        "hitCount": 1,
                        "moveId": 13,
                        "playerIndex": 0
                    }
                ],
                "openingType": "counter-attack",
                "playerIndex": 1,
                "startFrame": 3683,
                "startPercent": 71.55000305175781
            },
            {
                "currentPercent": 71.89999389648438,
                "didKill": false,
                "endFrame": 4121,
                "endPercent": 71.89999389648438,
                "lastHitBy": 1,
                "moves": [
                    {
                        "damage": 10.919998168945312,
                        "frame": 3995,
                        "hitCount": 1,
                        "moveId": 16,
                        "playerIndex": 1
                    }
                ],
                "openingType": "counter-attack",
                "playerIndex": 0,
                "startFrame": 3995,
                "startPercent": 60.97999572753906
            },
            {
                "currentPercent": 8,
                "didKill": false,
                "endFrame": 4515,
                "endPercent": 8,
                "lastHitBy": 0,
                "moves": [
                    {
                        "damage": 8,
                        "frame": 4390,
                        "hitCount": 1,
                        "moveId": 56,
                        "playerIndex": 0
                    }
                ],
                "openingType": "neutral-win",
                "playerIndex": 1,
                "startFrame": 4329,
                "startPercent": 0
            },
            {
                "currentPercent": 23.84000015258789,
                "didKill": false,
                "endFrame": 4577,
                "endPercent": 23.84000015258789,
                "lastHitBy": 0,
                "moves": [
                    {
                        "damage": 15.84000015258789,
                        "frame": 4519,
                        "hitCount": 1,
                        "moveId": 14,
                        "playerIndex": 0
                    }
                ],
                "openingType": "neutral-win",
                "playerIndex": 1,
                "startFrame": 4519,
                "startPercent": 8
            },
            {
                "currentPercent": 100.89999389648438,
                "didKill": true,
                "endFrame": 4715,
                "endPercent": 100.89999389648438,
                "lastHitBy": 1,
                "moves": [
                    {
                        "damage": 12,
                        "frame": 4553,
                        "hitCount": 1,
                        "moveId": 9,
                        "playerIndex": 1
                    },
                    {
                        "damage": 17,
                        "frame": 4654,
                        "hitCount": 1,
                        "moveId": 14,
                        "playerIndex": 1
                    }
                ],
                "openingType": "counter-attack",
                "playerIndex": 0,
                "startFrame": 4553,
                "startPercent": 71.89999389648438
            },
            {
                "currentPercent": 43.29999923706055,
                "didKill": false,
                "endFrame": 5038,
                "endPercent": 43.29999923706055,
                "lastHitBy": 0,
                "moves": [
                    {
                        "damage": 14,
                        "frame": 4941,
                        "hitCount": 1,
                        "moveId": 17,
                        "playerIndex": 0
                    },
                    {
                        "damage": 5.459999084472656,
                        "frame": 4967,
                        "hitCount": 1,
                        "moveId": 17,
                        "playerIndex": 0
                    }
                ],
                "openingType": "neutral-win",
                "playerIndex": 1,
                "startFrame": 4941,
                "startPercent": 23.84000015258789
            },
            {
                "currentPercent": 106.38999938964844,
                "didKill": false,
                "endFrame": 5763,
                "endPercent": 106.38999938964844,
                "lastHitBy": 0,
                "moves": [
                    {
                        "damage": 16,
                        "frame": 5050,
                        "hitCount": 1,
                        "moveId": 14,
                        "playerIndex": 0
                    },
                    {
                        "damage": 9.000003814697266,
                        "frame": 5239,
                        "hitCount": 1,
                        "moveId": 6,
                        "playerIndex": 0
                    },
                    {
                        "damage": 12.089996337890625,
                        "frame": 5304,
                        "hitCount": 1,
                        "moveId": 17,
                        "playerIndex": 0
                    },
                    {
                        "damage": 10,
                        "frame": 5456,
                        "hitCount": 1,
                        "moveId": 7,
                        "playerIndex": 0
                    },
                    {
                        "damage": 16,
                        "frame": 5530,
                        "hitCount": 1,
                        "moveId": 13,
                        "playerIndex": 0
                    }
                ],
                "openingType": "neutral-win",
                "playerIndex": 1,
                "startFrame": 5050,
                "startPercent": 43.29999923706055
            },
            {
                "currentPercent": 12,
                "didKill": false,
                "endFrame": 5266,
                "endPercent": 12,
                "lastHitBy": 1,
                "moves": [
                    {
                        "damage": 12,
                        "frame": 5134,
                        "hitCount": 1,
                        "moveId": 16,
                        "playerIndex": 1
                    }
                ],
                "openingType": "counter-attack",
                "playerIndex": 0,
                "startFrame": 5134,
                "startPercent": 0
            },
            {
                "currentPercent": 19,
                "didKill": false,
                "endFrame": 5866,
                "endPercent": 19,
                "lastHitBy": 1,
                "moves": [
                    {
                        "damage": 7,
                        "frame": 5755,
                        "hitCount": 1,
                        "moveId": 2,
                        "playerIndex": 1
                    }
                ],
                "openingType": "counter-attack",
                "playerIndex": 0,
                "startFrame": 5755,
                "startPercent": 12
            },
            {
                "currentPercent": 41.349998474121094,
                "didKill": false,
                "endFrame": 6426,
                "endPercent": 41.349998474121094,
                "lastHitBy": 1,
                "moves": [
                    {
                        "damage": 6.369998931884766,
                        "frame": 6048,
                        "hitCount": 1,
                        "moveId": 2,
                        "playerIndex": 1
                    },
                    {
                        "damage": 15.979999542236328,
                        "frame": 6100,
                        "hitCount": 1,
                        "moveId": 14,
                        "playerIndex": 1
                    }
                ],
                "openingType": "neutral-win",
                "playerIndex": 0,
                "startFrame": 6048,
                "startPercent": 19
            },
            {
                "currentPercent": 148.13999938964844,
                "didKill": true,
                "endFrame": 6777,
                "endPercent": 148.13999938964844,
                "lastHitBy": 0,
                "moves": [
                    {
                        "damage": 15.199996948242188,
                        "frame": 6347,
                        "hitCount": 1,
                        "moveId": 14,
                        "playerIndex": 0
                    },
                    {
                        "damage": 8.550003051757812,
                        "frame": 6550,
                        "hitCount": 1,
                        "moveId": 6,
                        "playerIndex": 0
                    },
                    {
                        "damage": 18,
                        "frame": 6630,
                        "hitCount": 1,
                        "moveId": 11,
                        "playerIndex": 0
                    }
                ],
                "openingType": "counter-attack",
                "playerIndex": 1,
                "startFrame": 6347,
                "startPercent": 106.38999938964844
            },
            {
                "currentPercent": 64.3499984741211,
                "didKill": false,
                "endFrame": 7263,
                "endPercent": 64.3499984741211,
                "lastHitBy": 1,
                "moves": [
                    {
                        "damage": 16,
                        "frame": 6928,
                        "hitCount": 1,
                        "moveId": 15,
                        "playerIndex": 1
                    },
                    {
                        "damage": 7,
                        "frame": 7210,
                        "hitCount": 1,
                        "moveId": 2,
                        "playerIndex": 1
                    }
                ],
                "openingType": "neutral-win",
                "playerIndex": 0,
                "startFrame": 6928,
                "startPercent": 41.349998474121094
            },
            {
                "currentPercent": 12.34999942779541,
                "didKill": false,
                "endFrame": 7277,
                "endPercent": 12.34999942779541,
                "lastHitBy": 0,
                "moves": [
                    {
                        "damage": 12.34999942779541,
                        "frame": 7178,
                        "hitCount": 1,
                        "moveId": 17,
                        "playerIndex": 0
                    }
                ],
                "openingType": "counter-attack",
                "playerIndex": 1,
                "startFrame": 7178,
                "startPercent": 0
            },
            {
                "currentPercent": 27.229999542236328,
                "didKill": false,
                "endFrame": 7388,
                "endPercent": 27.229999542236328,
                "lastHitBy": 0,
                "moves": [
                    {
                        "damage": 14.880000114440918,
                        "frame": 7290,
                        "hitCount": 1,
                        "moveId": 14,
                        "playerIndex": 0
                    }
                ],
                "openingType": "neutral-win",
                "playerIndex": 1,
                "startFrame": 7290,
                "startPercent": 12.34999942779541
            },
            {
                "currentPercent": 32.630001068115234,
                "didKill": false,
                "endFrame": 7498,
                "endPercent": 32.630001068115234,
                "lastHitBy": 0,
                "moves": [
                    {
                        "damage": 5.400001525878906,
                        "frame": 7428,
                        "hitCount": 1,
                        "moveId": 17,
                        "playerIndex": 0
                    }
                ],
                "openingType": "neutral-win",
                "playerIndex": 1,
                "startFrame": 7428,
                "startPercent": 27.229999542236328
            },
            {
                "currentPercent": 56.900001525878906,
                "didKill": false,
                "endFrame": 8123,
                "endPercent": 56.900001525878906,
                "lastHitBy": 0,
                "moves": [
                    {
                        "damage": 5,
                        "frame": 7551,
                        "hitCount": 1,
                        "moveId": 15,
                        "playerIndex": 0
                    },
                    {
                        "damage": 4.549999237060547,
                        "frame": 7632,
                        "hitCount": 1,
                        "moveId": 15,
                        "playerIndex": 0
                    },
                    {
                        "damage": 14.720001220703125,
                        "frame": 7739,
                        "hitCount": 1,
                        "moveId": 14,
                        "playerIndex": 0
                    }
                ],
                "openingType": "neutral-win",
                "playerIndex": 1,
                "startFrame": 7551,
                "startPercent": 32.630001068115234
            },
            {
                "currentPercent": 81.73001098632812,
                "didKill": false,
                "endFrame": 8037,
                "endPercent": 81.73001098632812,
                "lastHitBy": 1,
                "moves": [
                    {
                        "damage": 3.730010986328125,
                        "frame": 7864,
                        "hitCount": 4,
                        "moveId": 20,
                        "playerIndex": 1
                    },
                    {
                        "damage": 13.650001525878906,
                        "frame": 7890,
                        "hitCount": 1,
                        "moveId": 20,
                        "playerIndex": 1
                    }
                ],
                "openingType": "counter-attack",
                "playerIndex": 0,
                "startFrame": 7862,
                "startPercent": 64.3499984741211
            },
            {
                "currentPercent": 88.73001098632812,
                "didKill": false,
                "endFrame": 8265,
                "endPercent": 88.73001098632812,
                "lastHitBy": 1,
                "moves": [
                    {
                        "damage": 7,
                        "frame": 8108,
                        "hitCount": 1,
                        "moveId": 56,
                        "playerIndex": 1
                    }
                ],
                "openingType": "counter-attack",
                "playerIndex": 0,
                "startFrame": 8084,
                "startPercent": 81.73001098632812
            },
            {
                "currentPercent": 95.06999969482422,
                "didKill": false,
                "endFrame": 8520,
                "endPercent": 95.06999969482422,
                "lastHitBy": 0,
                "moves": [
                    {
                        "damage": 13.599998474121094,
                        "frame": 8180,
                        "hitCount": 1,
                        "moveId": 14,
                        "playerIndex": 0
                    },
                    {
                        "damage": 12.349998474121094,
                        "frame": 8280,
                        "hitCount": 3,
                        "moveId": 15,
                        "playerIndex": 0
                    },
                    {
                        "damage": 12.220001220703125,
                        "frame": 8413,
                        "hitCount": 1,
                        "moveId": 17,
                        "playerIndex": 0
                    }
                ],
                "openingType": "counter-attack",
                "playerIndex": 1,
                "startFrame": 8180,
                "startPercent": 56.900001525878906
            },
            {
                "currentPercent": 139.69000244140625,
                "didKill": false,
                "endFrame": 9112,
                "endPercent": 139.69000244140625,
                "lastHitBy": 0,
                "moves": [
                    {
                        "damage": 5.099998474121094,
                        "frame": 8535,
                        "hitCount": 1,
                        "moveId": 14,
                        "playerIndex": 0
                    },
                    {
                        "damage": 12.639999389648438,
                        "frame": 8579,
                        "hitCount": 1,
                        "moveId": 14,
                        "playerIndex": 0
                    },
                    {
                        "damage": 12.879997253417969,
                        "frame": 8793,
                        "hitCount": 1,
                        "moveId": 17,
                        "playerIndex": 0
                    },
                    {
                        "damage": 7.000007629394531,
                        "frame": 8914,
                        "hitCount": 1,
                        "moveId": 16,
                        "playerIndex": 0
                    },
                    {
                        "damage": 6,
                        "frame": 8958,
                        "hitCount": 1,
                        "moveId": 20,
                        "playerIndex": 0
                    }
                ],
                "openingType": "neutral-win",
                "playerIndex": 1,
                "startFrame": 8535,
                "startPercent": 95.06999969482422
            },
            {
                "currentPercent": 158.69000244140625,
                "didKill": true,
                "endFrame": 9567,
                "endPercent": 158.69000244140625,
                "lastHitBy": 0,
                "moves": [
                    {
                        "damage": 8,
                        "frame": 9229,
                        "hitCount": 1,
                        "moveId": 53,
                        "playerIndex": 0
                    },
                    {
                        "damage": 10,
                        "frame": 9394,
                        "hitCount": 1,
                        "moveId": 7,
                        "playerIndex": 0
                    }
                ],
                "openingType": "neutral-win",
                "playerIndex": 1,
                "startFrame": 9166,
                "startPercent": 139.69000244140625
            }
        ],
        "gameComplete": true,
        "lastFrame": 9567,
        "overall": [
            {
                "beneficialTradeRatio": {
                    "count": 0,
                    "ratio": null,
                    "total": 0
                },
                "conversionCount": 22,
                "counterHitRatio": {
                    "count": 7,
                    "ratio": 0.4375,
                    "total": 16
                },
                "damagePerOpening": {
                    "count": 510.9800033569336,
                    "ratio": 23.226363788951527,
                    "total": 22
                },
                "digitalInputsPerMinute": {
                    "count": 335,
                    "ratio": 125.54653341661461,
                    "total": 2.6683333333333334
                },
                "inputCounts": {
                    "buttons": 335,
                    "cstick": 26,
                    "joystick": 636,
                    "total": 1100,
                    "triggers": 103
                },
                "inputsPerMinute": {
                    "count": 1100,
                    "ratio": 412.2423485321674,
                    "total": 2.6683333333333334
                },
                "killCount": 4,
                "neutralWinRatio": {
                    "count": 15,
                    "ratio": 0.75,
                    "total": 20
                },
                "openingsPerKill": {
                    "count": 22,
                    "ratio": 5.5,
                    "total": 4
                },
                "playerIndex": 0,
                "successfulConversions": {
                    "count": 10,
                    "ratio": 0.45454545454545453,
                    "total": 22
                },
                "totalDamage": 510.9800033569336
            },
            {
                "beneficialTradeRatio": {
                    "count": 0,
                    "ratio": null,
                    "total": 0
                },
                "conversionCount": 14,
                "counterHitRatio": {
                    "count": 9,
                    "ratio": 0.5625,
                    "total": 16
                },
                "damagePerOpening": {
                    "count": 284.51000213623047,
                    "ratio": 20.32214300973075,
                    "total": 14
                },
                "digitalInputsPerMinute": {
                    "count": 314,
                    "ratio": 117.67645221736414,
                    "total": 2.6683333333333334
                },
                "inputCounts": {
                    "buttons": 314,
                    "cstick": 63,
                    "joystick": 298,
                    "total": 715,
                    "triggers": 40
                },
                "inputsPerMinute": {
                    "count": 715,
                    "ratio": 267.9575265459088,
                    "total": 2.6683333333333334
                },
                "killCount": 2,
                "neutralWinRatio": {
                    "count": 5,
                    "ratio": 0.25,
                    "total": 20
                },
                "openingsPerKill": {
                    "count": 14,
                    "ratio": 7,
                    "total": 2
                },
                "playerIndex": 1,
                "successfulConversions": {
                    "count": 8,
                    "ratio": 0.5714285714285714,
                    "total": 14
                },
                "totalDamage": 284.51000213623047
            }
        ],
        "playableFrameCount": 9606,
        "stocks": [
            {
                "count": 4,
                "currentPercent": 95.87999725341797,
                "deathAnimation": 4,
                "endFrame": 2210,
                "endPercent": 95.87999725341797,
                "playerIndex": 0,
                "startFrame": -123,
                "startPercent": 0
            },
            {
                "count": 4,
                "currentPercent": 96.73999786376953,
                "deathAnimation": 0,
                "endFrame": 1079,
                "endPercent": 96.73999786376953,
                "playerIndex": 1,
                "startFrame": -123,
                "startPercent": 0
            },
            {
                "count": 3,
                "currentPercent": 109.41000366210938,
                "deathAnimation": 0,
                "endFrame": 4073,
                "endPercent": 109.41000366210938,
                "playerIndex": 1,
                "startFrame": 1139,
                "startPercent": 0
            },
            {
                "count": 3,
                "currentPercent": 100.89999389648438,
                "deathAnimation": 1,
                "endFrame": 4715,
                "endPercent": 100.89999389648438,
                "playerIndex": 0,
                "startFrame": 2255,
                "startPercent": 0
            },
            {
                "count": 2,
                "currentPercent": 148.13999938964844,
                "deathAnimation": 7,
                "endFrame": 6777,
                "endPercent": 148.13999938964844,
                "playerIndex": 1,
                "startFrame": 4133,
                "startPercent": 0
            },
            {
                "count": 2,
                "currentPercent": 88.73001098632812,
                "deathAnimation": null,
                "endFrame": null,
                "endPercent": null,
                "playerIndex": 0,
                "startFrame": 4775,
                "startPercent": 0
            },
            {
                "count": 1,
                "currentPercent": 158.69000244140625,
                "deathAnimation": 0,
                "endFrame": 9567,
                "endPercent": 158.69000244140625,
                "playerIndex": 1,
                "startFrame": 6812,
                "startPercent": 0
            }
        ]
    }
}